[{"id":371928,"platform":"OPPOSTORE","account":"fengteng","password":"AE8254B10793685534C7A8C3338B2F8D","dataPassword":"","loginUrl":"https://e.oppomobile.com","reqJson":"{\"taskId\":371928,\"errorCode\":null,\"status\":3,\"statusDesc\":\"成功\",\"account\":\"fengteng\",\"platform\":\"OPPOSTORE\",\"filePathCatalog\":\"\",\"flag\":\"MSG\",\"isScreenshots\":1,\"isData\":1}","status":3,"failureTimes":0,"startTime":1563854400000,"getTaskTime":"2019-07-23 06:07:28","updateCookieTime":"2019-07-23 06:07:29","endTaskTime":0,"createTime":"2019-07-23 00:00:03","updateTime":"2019-07-23 06:07:29","statusDesc":"成功","errorCode":0,"category":"MSG","immediate":1,"flag":"MSG","isScreenshots":1,"isData":1,"remark":"","categoryName":"信息流","statusName":"完成","isScreenshotsName":"有截图","isDataName":"有数据"},{"id":371929,"platform":"OPPOSTORE","account":"棒播","password":"5136862423482667","dataPassword":"","loginUrl":"https://e.oppomobile.com","reqJson":"{\"taskId\":371929,\"errorCode\":null,\"status\":3,\"statusDesc\":\"成功\",\"account\":\"棒播\",\"platform\":\"OPPOSTORE\",\"filePathCatalog\":\"\",\"flag\":\"MSG2\",\"isScreenshots\":1,\"isData\":1}","status":3,"failureTimes":0,"startTime":1563854400000,"getTaskTime":"2019-07-23 06:08:18","updateCookieTime":"2019-07-23 06:08:18","endTaskTime":0,"createTime":"2019-07-23 00:00:03","updateTime":"2019-07-23 06:08:18","statusDesc":"成功","errorCode":0,"category":"MSG","immediate":1,"flag":"MSG2","isScreenshots":1,"isData":1,"remark":"","categoryName":"信息流","statusName":"完成","isScreenshotsName":"有截图","isDataName":"有数据"},{"id":371930,"platform":"OPPOSTORE","account":"kuaikan","password":"DBB1CE85D5C311BA","dataPassword":"","loginUrl":"https://e.oppomobile.com","reqJson":"{\"taskId\":371930,\"errorCode\":null,\"status\":3,\"statusDesc\":\"成功\",\"account\":\"kuaikan\",\"platform\":\"OPPOSTORE\",\"filePathCatalog\":\"\",\"flag\":\"CPA\",\"isScreenshots\":1,\"isData\":1}","status":3,"failureTimes":0,"startTime":1563854400000,"getTaskTime":"2019-07-23 06:08:33","updateCookieTime":"2019-07-23 06:08:33","endTaskTime":0,"createTime":"2019-07-23 00:00:03","updateTime":"2019-07-23 06:08:33","statusDesc":"成功","errorCode":0,"category":"MSG","immediate":1,"flag":"CPA","isScreenshots":1,"isData":1,"remark":"","categoryName":"信息流","statusName":"完成","isScreenshotsName":"有截图","isDataName":"有数据"},{"id":371931,"platform":"OPPOSTORE","account":"naifei","password":"71009F0CE0A0655C","dataPassword":"","loginUrl":"https://e.oppomobile.com","reqJson":"{\"taskId\":371931,\"errorCode\":null,\"status\":3,\"statusDesc\":\"成功\",\"account\":\"naifei\",\"platform\":\"OPPOSTORE\",\"filePathCatalog\":\"\",\"flag\":\"MSG\",\"isScreenshots\":1,\"isData\":1}","status":3,"failureTimes":0,"startTime":1563854400000,"getTaskTime":"2019-07-23 06:09:09","updateCookieTime":"2019-07-23 06:09:09","endTaskTime":0,"createTime":"2019-07-23 00:00:03","updateTime":"2019-07-23 06:09:09","statusDesc":"成功","errorCode":0,"category":"MSG","immediate":1,"flag":"MSG","isScreenshots":1,"isData":1,"remark":"","categoryName":"信息流","statusName":"完成","isScreenshotsName":"有截图","isDataName":"有数据"},{"id":371932,"platform":"OPPOSTORE","account":"haohaozhu","password":"841C1D94C42F89A0BA5CB9EAB7F534C7","dataPassword":"","loginUrl":"https://e.oppomobile.com","reqJson":"{\"taskId\":371932,\"errorCode\":null,\"status\":3,\"statusDesc\":\"成功\",\"account\":\"haohaozhu\",\"platform\":\"OPPOSTORE\",\"filePathCatalog\":\"\",\"flag\":\"CPA\",\"isScreenshots\":1,\"isData\":1}","status":3,"failureTimes":0,"startTime":1563854400000,"getTaskTime":"2019-07-23 06:09:26","updateCookieTime":"2019-07-23 06:09:26","endTaskTime":0,"createTime":"2019-07-23 00:00:03","updateTime":"2019-07-23 06:09:26","statusDesc":"成功","errorCode":0,"category":"MSG","immediate":1,"flag":"CPA","isScreenshots":1,"isData":1,"remark":"","categoryName":"信息流","statusName":"完成","isScreenshotsName":"有截图","isDataName":"有数据"},{"id":371933,"platform":"OPPOSTORE","account":"mankezhan","password":"A8501FE46F598F227E8A506D12F32436","dataPassword":"","loginUrl":"https://e.oppomobile.com","reqJson":"{\"taskId\":371933,\"errorCode\":null,\"status\":3,\"statusDesc\":\"成功\",\"account\":\"mankezhan\",\"platform\":\"OPPOSTORE\",\"filePathCatalog\":\"\",\"flag\":\"MSG\",\"isScreenshots\":1,\"isData\":1}","status":3,"failureTimes":0,"startTime":1563854400000,"getTaskTime":"2019-07-23 06:10:53","updateCookieTime":"2019-07-23 06:10:53","endTaskTime":0,"createTime":"2019-07-23 00:00:03","updateTime":"2019-07-23 06:10:53","statusDesc":"成功","errorCode":0,"category":"MSG","immediate":1,"flag":"MSG","isScreenshots":1,"isData":1,"remark":"","categoryName":"信息流","statusName":"完成","isScreenshotsName":"有截图","isDataName":"有数据"},{"id":371934,"platform":"OPPOSTORE","account":"kanmanhua2","password":"10FDD41FD162D1D5B1EF1414B199F676","dataPassword":"","loginUrl":"https://e.oppomobile.com","reqJson":"{\"taskId\":371934,\"errorCode\":null,\"status\":3,\"statusDesc\":\"成功\",\"account\":\"kanmanhua2\",\"platform\":\"OPPOSTORE\",\"filePathCatalog\":\"\",\"flag\":\"MSG2\",\"isScreenshots\":1,\"isData\":1}","status":3,"failureTimes":0,"startTime":1563854400000,"getTaskTime":"2019-07-23 06:10:58","updateCookieTime":"2019-07-23 06:10:58","endTaskTime":0,"createTime":"2019-07-23 00:00:03","updateTime":"2019-07-23 06:10:58","statusDesc":"成功","errorCode":0,"category":"MSG","immediate":1,"flag":"MSG2","isScreenshots":1,"isData":1,"remark":"","categoryName":"信息流","statusName":"完成","isScreenshotsName":"有截图","isDataName":"有数据"},{"id":371935,"platform":"OPPOSTORE","account":"manhuatai2","password":"8D9EDA174A265E71C48C81A9DC81C307","dataPassword":"","loginUrl":"https://e.oppomobile.com","reqJson":"{\"taskId\":371935,\"errorCode\":null,\"status\":3,\"statusDesc\":\"成功\",\"account\":\"manhuatai2\",\"platform\":\"OPPOSTORE\",\"filePathCatalog\":\"\",\"flag\":\"CPA\",\"isScreenshots\":1,\"isData\":1}","status":3,"failureTimes":0,"startTime":1563854400000,"getTaskTime":"2019-07-23 06:11:09","updateCookieTime":"2019-07-23 06:11:10","endTaskTime":0,"createTime":"2019-07-23 00:00:03","updateTime":"2019-07-23 06:11:10","statusDesc":"成功","errorCode":0,"category":"MSG","immediate":1,"flag":"CPA","isScreenshots":1,"isData":1,"remark":"","categoryName":"信息流","statusName":"完成","isScreenshotsName":"有截图","isDataName":"有数据"},{"id":371936,"platform":"OPPOSTORE","account":"shenmanhua2","password":"1BA0C0469980696666DFAEB27CE415E7","dataPassword":"","loginUrl":"https://e.oppomobile.com","reqJson":"{\"taskId\":371936,\"errorCode\":null,\"status\":3,\"statusDesc\":\"成功\",\"account\":\"shenmanhua2\",\"platform\":\"OPPOSTORE\",\"filePathCatalog\":\"\",\"flag\":\"CPA\",\"isScreenshots\":1,\"isData\":1}","status":3,"failureTimes":0,"startTime":1563854400000,"getTaskTime":"2019-07-23 06:12:03","updateCookieTime":"2019-07-23 06:12:03","endTaskTime":0,"createTime":"2019-07-23 00:00:03","updateTime":"2019-07-23 06:12:03","statusDesc":"成功","errorCode":0,"category":"MSG","immediate":1,"flag":"CPA","isScreenshots":1,"isData":1,"remark":"","categoryName":"信息流","statusName":"完成","isScreenshotsName":"有截图","isDataName":"有数据"},{"id":371937,"platform":"OPPOSTORE","account":"zhiyinmanhua2","password":"5CAEE33F27331414192FFDCF5F6E988D","dataPassword":"","loginUrl":"https://e.oppomobile.com","reqJson":"{\"taskId\":371937,\"errorCode\":null,\"status\":3,\"statusDesc\":\"成功\",\"account\":\"zhiyinmanhua2\",\"platform\":\"OPPOSTORE\",\"filePathCatalog\":\"\",\"flag\":\"CPA\",\"isScreenshots\":1,\"isData\":1}","status":3,"failureTimes":0,"startTime":1563854400000,"getTaskTime":"2019-07-23 06:12:56","updateCookieTime":"2019-07-23 06:12:56","endTaskTime":0,"createTime":"2019-07-23 00:00:03","updateTime":"2019-07-23 06:12:56","statusDesc":"成功","errorCode":0,"category":"MSG","immediate":1,"flag":"CPA","isScreenshots":1,"isData":1,"remark":"","categoryName":"信息流","statusName":"完成","isScreenshotsName":"有截图","isDataName":"有数据"},{"id":371938,"platform":"OPPOSTORE","account":"youlechang","password":"3E317029E1FE3CAD50A28B03E77042F5","dataPassword":"","loginUrl":"https://e.oppomobile.com","reqJson":"{\"taskId\":371938,\"errorCode\":null,\"status\":3,\"statusDesc\":\"成功\",\"account\":\"youlechang\",\"platform\":\"OPPOSTORE\",\"filePathCatalog\":\"\",\"flag\":\"MSG2\",\"isScreenshots\":1,\"isData\":1}","status":3,"failureTimes":0,"startTime":1563854400000,"getTaskTime":"2019-07-23 06:13:56","updateCookieTime":"2019-07-23 06:13:56","endTaskTime":0,"createTime":"2019-07-23 00:00:03","updateTime":"2019-07-23 06:13:56","statusDesc":"成功","errorCode":0,"category":"MSG","immediate":1,"flag":"MSG2","isScreenshots":1,"isData":1,"remark":"","categoryName":"信息流","statusName":"完成","isScreenshotsName":"有截图","isDataName":"有数据"},{"id":371939,"platform":"OPPOSTORE","account":"包找钱01","password":"E1EC23AF032B6CE0A23718F8E17A91E9","dataPassword":"","loginUrl":"https://e.oppomobile.com","reqJson":"{\"taskId\":371939,\"errorCode\":null,\"status\":3,\"statusDesc\":\"成功\",\"account\":\"包找钱01\",\"platform\":\"OPPOSTORE\",\"filePathCatalog\":\"\",\"flag\":\"MSG2\",\"isScreenshots\":1,\"isData\":1}","status":3,"failureTimes":0,"startTime":1563854400000,"getTaskTime":"2019-07-23 06:14:47","updateCookieTime":"2019-07-23 06:14:47","endTaskTime":0,"createTime":"2019-07-23 00:00:03","updateTime":"2019-07-23 06:14:47","statusDesc":"成功","errorCode":0,"category":"MSG","immediate":1,"flag":"MSG2","isScreenshots":1,"isData":1,"remark":"","categoryName":"信息流","statusName":"完成","isScreenshotsName":"有截图","isDataName":"有数据"},{"id":371940,"platform":"OPPOSTORE","account":"SEHH001-完美志愿-分发","password":"8D9436F86454F94B6CF33E12663D157E","dataPassword":"","loginUrl":"https://e.oppomobile.com","reqJson":"{\"taskId\":371940,\"errorCode\":null,\"status\":3,\"statusDesc\":\"成功\",\"account\":\"SEHH001-完美志愿-分发\",\"platform\":\"OPPOSTORE\",\"filePathCatalog\":\"\",\"flag\":\"CPA\",\"isScreenshots\":1,\"isData\":1}","status":3,"failureTimes":0,"startTime":1563854400000,"getTaskTime":"2019-07-23 06:15:35","updateCookieTime":"2019-07-23 06:15:35","endTaskTime":0,"createTime":"2019-07-23 00:00:03","updateTime":"2019-07-23 06:15:35","statusDesc":"成功","errorCode":0,"category":"MSG","immediate":1,"flag":"CPA","isScreenshots":1,"isData":1,"remark":"","categoryName":"信息流","statusName":"完成","isScreenshotsName":"有截图","isDataName":"有数据"},{"id":371941,"platform":"OPPOSTORE","account":"他趣1","password":"4C3B26BF7DA90EAE","dataPassword":"","loginUrl":"https://e.oppomobile.com","reqJson":"{\"taskId\":371941,\"errorCode\":null,\"status\":3,\"statusDesc\":\"成功\",\"account\":\"他趣1\",\"platform\":\"OPPOSTORE\",\"filePathCatalog\":\"\",\"flag\":\"MSG2\",\"isScreenshots\":1,\"isData\":1}","status":3,"failureTimes":0,"startTime":1563854400000,"getTaskTime":"2019-07-23 06:16:28","updateCookieTime":"2019-07-23 06:16:28","endTaskTime":0,"createTime":"2019-07-23 00:00:03","updateTime":"2019-07-23 06:16:28","statusDesc":"成功","errorCode":0,"category":"MSG","immediate":1,"flag":"MSG2","isScreenshots":1,"isData":1,"remark":"","categoryName":"信息流","statusName":"完成","isScreenshotsName":"有截图","isDataName":"有数据"},{"id":371942,"platform":"OPPOSTORE","account":"包找钱1","password":"01EB57C5FBE411DB","dataPassword":"","loginUrl":"https://e.oppomobile.com","reqJson":"{\"taskId\":371942,\"errorCode\":null,\"status\":3,\"statusDesc\":\"成功\",\"account\":\"包找钱1\",\"platform\":\"OPPOSTORE\",\"filePathCatalog\":\"\",\"flag\":\"MSG\",\"isScreenshots\":1,\"isData\":1}","status":3,"failureTimes":0,"startTime":1563854400000,"getTaskTime":"2019-07-23 06:16:35","updateCookieTime":"2019-07-23 06:16:35","endTaskTime":0,"createTime":"2019-07-23 00:00:03","updateTime":"2019-07-23 06:16:35","statusDesc":"成功","errorCode":0,"category":"MSG","immediate":1,"flag":"MSG","isScreenshots":1,"isData":1,"remark":"","categoryName":"信息流","statusName":"完成","isScreenshotsName":"有截图","isDataName":"有数据"},{"id":371955,"platform":"OPPOSTORE","account":"SZHH-华润通-分发","password":"BD1080229623C385753AF0413540C9D8","dataPassword":"","loginUrl":"https://e.oppomobile.com","reqJson":"{\"taskId\":371955,\"errorCode\":null,\"status\":3,\"statusDesc\":\"成功\",\"account\":\"SZHH-华润通-分发\",\"platform\":\"OPPOSTORE\",\"filePathCatalog\":\"\",\"flag\":\"MSG2\",\"isScreenshots\":1,\"isData\":1}","status":3,"failureTimes":0,"startTime":1563854400000,"getTaskTime":"2019-07-23 06:34:07","updateCookieTime":"2019-07-23 06:34:07","endTaskTime":0,"createTime":"2019-07-23 00:00:03","updateTime":"2019-07-23 06:34:07","statusDesc":"成功","errorCode":0,"category":"MSG","immediate":1,"flag":"MSG2","isScreenshots":1,"isData":1,"remark":"","categoryName":"信息流","statusName":"完成","isScreenshotsName":"有截图","isDataName":"有数据"},{"id":371972,"platform":"OPPOSTORE","account":"quanmin","password":"182E4FFF6152E285EAB6BAC44E055767","dataPassword":"","loginUrl":"https://e.oppomobile.com","reqJson":"{\"taskId\":371972,\"errorCode\":null,\"status\":3,\"statusDesc\":\"成功\",\"account\":\"quanmin\",\"platform\":\"OPPOSTORE\",\"filePathCatalog\":\"\",\"flag\":\"MSG2\",\"isScreenshots\":1,\"isData\":1}","status":3,"failureTimes":0,"startTime":1563854400000,"getTaskTime":"2019-07-23 01:05:30","updateCookieTime":"2019-07-23 01:05:30","endTaskTime":0,"createTime":"2019-07-23 00:00:03","updateTime":"2019-07-23 01:05:30","statusDesc":"成功","errorCode":0,"category":"MSG","immediate":1,"flag":"MSG2","isScreenshots":1,"isData":1,"remark":"","categoryName":"信息流","statusName":"完成","isScreenshotsName":"有截图","isDataName":"有数据"},{"id":371973,"platform":"OPPOSTORE","account":"liuliu123","password":"CAD530DEAF92C45093D421922E38244D","dataPassword":"","loginUrl":"https://e.oppomobile.com","reqJson":"{\"taskId\":371973,\"errorCode\":null,\"status\":3,\"statusDesc\":\"成功\",\"account\":\"liuliu123\",\"platform\":\"OPPOSTORE\",\"filePathCatalog\":\"\",\"flag\":\"MSG2\",\"isScreenshots\":1,\"isData\":1}","status":3,"failureTimes":0,"startTime":1563854400000,"getTaskTime":"2019-07-23 01:06:56","updateCookieTime":"2019-07-23 01:06:57","endTaskTime":0,"createTime":"2019-07-23 00:00:03","updateTime":"2019-07-23 01:06:57","statusDesc":"成功","errorCode":0,"category":"MSG","immediate":1,"flag":"MSG2","isScreenshots":1,"isData":1,"remark":"","categoryName":"信息流","statusName":"完成","isScreenshotsName":"有截图","isDataName":"有数据"},{"id":371974,"platform":"OPPOSTORE","account":"多融理财1","password":"AADB4B658757CD79AD0903FCBDF8ECE8","dataPassword":"","loginUrl":"https://e.oppomobile.com","reqJson":"{\"taskId\":371974,\"errorCode\":null,\"status\":3,\"statusDesc\":\"成功\",\"account\":\"多融理财1\",\"platform\":\"OPPOSTORE\",\"filePathCatalog\":\"\",\"flag\":\"MSG2\",\"isScreenshots\":1,\"isData\":1}","status":3,"failureTimes":0,"startTime":1563854400000,"getTaskTime":"2019-07-23 01:08:56","updateCookieTime":"2019-07-23 01:08:56","endTaskTime":0,"createTime":"2019-07-23 00:00:03","updateTime":"2019-07-23 01:08:56","statusDesc":"成功","errorCode":0,"category":"MSG","immediate":1,"flag":"MSG2","isScreenshots":1,"isData":1,"remark":"","categoryName":"信息流","statusName":"完成","isScreenshotsName":"有截图","isDataName":"有数据"},{"id":371975,"platform":"OPPOSTORE","account":"lexiusp1","password":"49CE101A60333E30DCF53BC9ADD63D16","dataPassword":"","loginUrl":"https://e.oppomobile.com","reqJson":"{\"taskId\":371975,\"errorCode\":null,\"status\":3,\"statusDesc\":\"成功\",\"account\":\"lexiusp1\",\"platform\":\"OPPOSTORE\",\"filePathCatalog\":\"\",\"flag\":\"MSG\",\"isScreenshots\":1,\"isData\":1}","status":3,"failureTimes":0,"startTime":1563854400000,"getTaskTime":"2019-07-23 01:10:24","updateCookieTime":"2019-07-23 01:10:24","endTaskTime":0,"createTime":"2019-07-23 00:00:03","updateTime":"2019-07-23 01:10:24","statusDesc":"成功","errorCode":0,"category":"MSG","immediate":1,"flag":"MSG","isScreenshots":1,"isData":1,"remark":"","categoryName":"信息流","statusName":"完成","isScreenshotsName":"有截图","isDataName":"有数据"},{"id":371976,"platform":"OPPOSTORE","account":"小马资本","password":"C5419AF58BB4BCBD56B06B9A6E997B9F","dataPassword":"","loginUrl":"https://e.oppomobile.com","reqJson":"{\"taskId\":371976,\"errorCode\":null,\"status\":3,\"statusDesc\":\"成功\",\"account\":\"小马资本\",\"platform\":\"OPPOSTORE\",\"filePathCatalog\":\"\",\"flag\":\"MSG\",\"isScreenshots\":1,\"isData\":1}","status":3,"failureTimes":0,"startTime":1563854400000,"getTaskTime":"2019-07-23 01:12:38","updateCookieTime":"2019-07-23 01:12:38","endTaskTime":0,"createTime":"2019-07-23 00:00:03","updateTime":"2019-07-23 01:12:38","statusDesc":"成功","errorCode":0,"category":"MSG","immediate":1,"flag":"MSG","isScreenshots":1,"isData":1,"remark":"","categoryName":"信息流","statusName":"完成","isScreenshotsName":"有截图","isDataName":"有数据"},{"id":371977,"platform":"OPPOSTORE","account":"多融理财2","password":"0B5777B56B0464C5","dataPassword":"","loginUrl":"https://e.oppomobile.com","reqJson":"{\"taskId\":371977,\"errorCode\":null,\"status\":3,\"statusDesc\":\"成功\",\"account\":\"多融理财2\",\"platform\":\"OPPOSTORE\",\"filePathCatalog\":\"\",\"flag\":\"MSG\",\"isScreenshots\":1,\"isData\":1}","status":3,"failureTimes":0,"startTime":1563854400000,"getTaskTime":"2019-07-23 01:14:02","updateCookieTime":"2019-07-23 01:14:02","endTaskTime":0,"createTime":"2019-07-23 00:00:03","updateTime":"2019-07-23 01:14:02","statusDesc":"成功","errorCode":0,"category":"MSG","immediate":1,"flag":"MSG","isScreenshots":1,"isData":1,"remark":"","categoryName":"信息流","statusName":"完成","isScreenshotsName":"有截图","isDataName":"有数据"},{"id":372011,"platform":"OPPOSTORE","account":"陌声-分发","password":"67E954F79E9E72A1","dataPassword":"","loginUrl":"http://e.oppomobile.com","reqJson":"{\"taskId\":372011,\"errorCode\":null,\"status\":3,\"statusDesc\":\"成功\",\"account\":\"陌声-分发\",\"platform\":\"OPPOSTORE\",\"filePathCatalog\":\"\",\"flag\":\"MSG\",\"isScreenshots\":1,\"isData\":1}","status":3,"failureTimes":0,"startTime":1563854400000,"getTaskTime":"2019-07-23 02:20:19","updateCookieTime":"2019-07-23 02:20:19","endTaskTime":0,"createTime":"2019-07-23 00:00:03","updateTime":"2019-07-23 02:20:19","statusDesc":"成功","errorCode":0,"category":"MSG","immediate":1,"flag":"MSG","isScreenshots":1,"isData":1,"remark":"","categoryName":"信息流","statusName":"完成","isScreenshotsName":"有截图","isDataName":"有数据"},{"id":372059,"platform":"OPPOSTORE","account":"EHH003-章鱼输入法-分发","password":"0E9AFCF571ECCE7E83B33ACC1D0A225D","dataPassword":"","loginUrl":"http://e.oppomobile.com","reqJson":"{\"taskId\":372059,\"errorCode\":null,\"status\":3,\"statusDesc\":\"成功\",\"account\":\"EHH003-章鱼输入法-分发\",\"platform\":\"OPPOSTORE\",\"filePathCatalog\":\"\",\"flag\":\"MSG\",\"isScreenshots\":1,\"isData\":1}","status":3,"failureTimes":0,"startTime":1563854400000,"getTaskTime":"2019-07-23 03:29:08","updateCookieTime":"2019-07-23 03:29:08","endTaskTime":0,"createTime":"2019-07-23 00:00:03","updateTime":"2019-07-23 03:29:08","statusDesc":"成功","errorCode":0,"category":"MSG","immediate":1,"flag":"MSG","isScreenshots":1,"isData":1,"remark":"","categoryName":"信息流","statusName":"完成","isScreenshotsName":"有截图","isDataName":"有数据"},{"id":372066,"platform":"OPPOSTORE","account":"Q-热门小说吧-分发","password":"67E954F79E9E72A1","dataPassword":"","loginUrl":"http://e.oppomobile.com","reqJson":"{\"taskId\":372066,\"errorCode\":null,\"status\":3,\"statusDesc\":\"成功\",\"account\":\"Q-热门小说吧-分发\",\"platform\":\"OPPOSTORE\",\"filePathCatalog\":\"\",\"flag\":\"CPA\",\"isScreenshots\":1,\"isData\":1}","status":3,"failureTimes":0,"startTime":1563854400000,"getTaskTime":"2019-07-23 03:37:23","updateCookieTime":"2019-07-23 03:37:23","endTaskTime":0,"createTime":"2019-07-23 00:00:03","updateTime":"2019-07-23 03:37:23","statusDesc":"成功","errorCode":0,"category":"MSG","immediate":1,"flag":"CPA","isScreenshots":1,"isData":1,"remark":"","categoryName":"信息流","statusName":"完成","isScreenshotsName":"有截图","isDataName":"有数据"},{"id":372068,"platform":"OPPOSTORE","account":"Q-西瓜免费小说-分发","password":"67E954F79E9E72A1","dataPassword":"","loginUrl":"http://e.oppomobile.com","reqJson":"{\"taskId\":372068,\"errorCode\":null,\"status\":3,\"statusDesc\":\"成功\",\"account\":\"Q-西瓜免费小说-分发\",\"platform\":\"OPPOSTORE\",\"filePathCatalog\":\"\",\"flag\":\"CPA\",\"isScreenshots\":1,\"isData\":1}","status":3,"failureTimes":0,"startTime":1563854400000,"getTaskTime":"2019-07-23 03:40:05","updateCookieTime":"2019-07-23 03:40:05","endTaskTime":0,"createTime":"2019-07-23 00:00:03","updateTime":"2019-07-23 03:40:05","statusDesc":"成功","errorCode":0,"category":"MSG","immediate":1,"flag":"CPA","isScreenshots":1,"isData":1,"remark":"","categoryName":"信息流","statusName":"完成","isScreenshotsName":"有截图","isDataName":"有数据"},{"id":372077,"platform":"OPPOSTORE","account":"Q-马克购物清单-商店","password":"67E954F79E9E72A1","dataPassword":"","loginUrl":"http://e.oppomobile.com","reqJson":"{\"taskId\":372077,\"errorCode\":null,\"status\":3,\"statusDesc\":\"成功\",\"account\":\"Q-马克购物清单-商店\",\"platform\":\"OPPOSTORE\",\"filePathCatalog\":\"\",\"flag\":\"CPA\",\"isScreenshots\":1,\"isData\":1}","status":3,"failureTimes":0,"startTime":1563854400000,"getTaskTime":"2019-07-23 03:48:55","updateCookieTime":"2019-07-23 03:48:55","endTaskTime":0,"createTime":"2019-07-23 00:00:03","updateTime":"2019-07-23 03:48:55","statusDesc":"成功","errorCode":0,"category":"MSG","immediate":1,"flag":"CPA","isScreenshots":1,"isData":1,"remark":"","categoryName":"信息流","statusName":"完成","isScreenshotsName":"有截图","isDataName":"有数据"},{"id":372095,"platform":"OPPOSTORE","account":"EHH004-天气君-分发","password":"101858D999D1235A","dataPassword":"","loginUrl":"http://e.oppomobile.com","reqJson":"{\"taskId\":372095,\"errorCode\":null,\"status\":3,\"statusDesc\":\"成功\",\"account\":\"EHH004-天气君-分发\",\"platform\":\"OPPOSTORE\",\"filePathCatalog\":\"\",\"flag\":\"MSG2\",\"isScreenshots\":1,\"isData\":1}","status":3,"failureTimes":0,"startTime":1563854400000,"getTaskTime":"2019-07-23 04:10:23","updateCookieTime":"2019-07-23 04:10:23","endTaskTime":0,"createTime":"2019-07-23 00:00:03","updateTime":"2019-07-23 04:10:23","statusDesc":"成功","errorCode":0,"category":"MSG","immediate":1,"flag":"MSG2","isScreenshots":1,"isData":1,"remark":"","categoryName":"信息流","statusName":"完成","isScreenshotsName":"有截图","isDataName":"有数据"},{"id":372147,"platform":"OPPOSTORE","account":"mianfeixs","password":"D8C59F597CBEF0A37422CE3BFB33AF22","dataPassword":"","loginUrl":"http://e.oppomobile.com","reqJson":"{\"taskId\":372147,\"errorCode\":null,\"status\":3,\"statusDesc\":\"成功\",\"account\":\"mianfeixs\",\"platform\":\"OPPOSTORE\",\"filePathCatalog\":\"\",\"flag\":\"MSG\",\"isScreenshots\":1,\"isData\":1}","status":3,"failureTimes":0,"startTime":1563854400000,"getTaskTime":"2019-07-23 05:24:40","updateCookieTime":"2019-07-23 05:24:40","endTaskTime":0,"createTime":"2019-07-23 00:00:03","updateTime":"2019-07-23 05:24:40","statusDesc":"成功","errorCode":0,"category":"MSG","immediate":1,"flag":"MSG","isScreenshots":1,"isData":1,"remark":"","categoryName":"信息流","statusName":"完成","isScreenshotsName":"有截图","isDataName":"有数据"},{"id":372149,"platform":"OPPOSTORE","account":"mfxsqj","password":"2C44A54DF3D2CE9D","dataPassword":"","loginUrl":"http://e.oppomobile.com","reqJson":"{\"taskId\":372149,\"errorCode\":null,\"status\":3,\"statusDesc\":\"成功\",\"account\":\"mfxsqj\",\"platform\":\"OPPOSTORE\",\"filePathCatalog\":\"\",\"flag\":\"CPA\",\"isScreenshots\":1,\"isData\":1}","status":3,"failureTimes":0,"startTime":1563854400000,"getTaskTime":"2019-07-23 05:26:58","updateCookieTime":"2019-07-23 05:26:58","endTaskTime":0,"createTime":"2019-07-23 00:00:03","updateTime":"2019-07-23 05:26:58","statusDesc":"成功","errorCode":0,"category":"MSG","immediate":1,"flag":"CPA","isScreenshots":1,"isData":1,"remark":"","categoryName":"信息流","statusName":"完成","isScreenshotsName":"有截图","isDataName":"有数据"},{"id":372325,"platform":"OPPOSTORE","account":"Q-杭州煎饼网络技术有限公司-信息流","password":"0B85197E431F8F12","dataPassword":"","loginUrl":"http://e.oppomobile.com","reqJson":"{\"taskId\":372325,\"errorCode\":null,\"status\":3,\"statusDesc\":\"成功\",\"account\":\"Q-杭州煎饼网络技术有限公司-信息流\",\"platform\":\"OPPOSTORE\",\"filePathCatalog\":\"\",\"flag\":\"MSG2\",\"isScreenshots\":1,\"isData\":1}","status":3,"failureTimes":0,"startTime":1563854400000,"getTaskTime":"2019-07-23 03:41:22","updateCookieTime":"2019-07-23 03:41:22","endTaskTime":0,"createTime":"2019-07-23 00:00:03","updateTime":"2019-07-23 03:41:22","statusDesc":"成功","errorCode":0,"category":"MSG","immediate":1,"flag":"MSG2","isScreenshots":1,"isData":1,"remark":"","categoryName":"信息流","statusName":"完成","isScreenshotsName":"有截图","isDataName":"有数据"},{"id":372546,"platform":"OPPOSTORE","account":"ANG-十秒记账-信息流","password":"C918857AB108FF4C49A59DCBD58EE603","dataPassword":"","loginUrl":"http://e.oppomobile.com","reqJson":"{\"taskId\":372546,\"errorCode\":null,\"status\":3,\"statusDesc\":\"成功\",\"account\":\"ANG-十秒记账-信息流\",\"platform\":\"OPPOSTORE\",\"filePathCatalog\":\"\",\"flag\":\"MSG\",\"isScreenshots\":1,\"isData\":1}","status":3,"failureTimes":0,"startTime":1563854400000,"getTaskTime":"2019-07-23 02:57:54","updateCookieTime":"2019-07-23 02:57:54","endTaskTime":0,"createTime":"2019-07-23 00:00:03","updateTime":"2019-07-23 02:57:54","statusDesc":"成功","errorCode":0,"category":"MSG","immediate":1,"flag":"MSG","isScreenshots":1,"isData":1,"remark":"","categoryName":"信息流","statusName":"完成","isScreenshotsName":"有截图","isDataName":"有数据"}]